<?xml version="1.0" encoding="utf-8"?>
<resources xmlns:xliff="urn:oasis:names:tc:xliff:document:1.2">
    <string name="actionbar_share">"Compartir"</string>
    <string name="actionbar_web_search">"Buscador web"</string>
    <string name="accessibility_content_view">"Visualizador web"</string>
    <string name="date_picker_dialog_set">"Asignar"</string>
    <string name="date_picker_dialog_clear">"Limpiar"</string>
    <string name="date_picker_dialog_title">"Ajustar fecha"</string>
    <string name="date_time_picker_dialog_title">"Ajustar fecha y hora"</string>
    <string name="time_picker_dialog_title">"Ajustar hora"</string>
    <string name="time_picker_dialog_am">"AM"</string>
    <string name="time_picker_dialog_pm">"PM"</string>
    <string name="time_picker_dialog_hour_minute_separator">":"</string>
    <string name="time_picker_dialog_minute_second_separator">":"</string>
    <string name="time_picker_dialog_second_subsecond_separator">"."</string>
    <string name="month_picker_dialog_title">"Ajustar mes"</string>
    <string name="week_picker_dialog_title">"Ajustar semana"</string>
    <string name="accessibility_datetime_picker_date">"Fecha"</string>
    <string name="accessibility_datetime_picker_time">"Hora"</string>
    <string name="accessibility_date_picker_month">"Mes"</string>
    <string name="accessibility_date_picker_week">"Semana"</string>
    <string name="accessibility_date_picker_year">"Año"</string>
    <string name="accessibility_time_picker_hour">"Hora"</string>
    <string name="accessibility_time_picker_minute">"Minuto"</string>
    <string name="accessibility_time_picker_second">"Segundo"</string>
    <string name="accessibility_time_picker_milli">"Milisegundo"</string>
    <string name="accessibility_time_picker_ampm">"AM/PM"</string>
    <string name="media_player_error_title">"No se puede reproducir vídeos"</string>
    <string name="media_player_error_text_invalid_progressive_playback">"Lo sentimos, este vídeo no se puede reproducir en este dispositivo."</string>
    <string name="media_player_error_text_unknown">"Lo sentimos, este vídeo no puede ser reproducido."</string>
    <string name="media_player_error_button">"OK"</string>
    <string name="media_player_loading_video">"Cargando vídeo"</string>
    <string name="profiler_started_toast">"Analizador iniciado"</string>
    <string name="profiler_stopped_toast">"Analizador finalizado. Resultados guardados en %1$s."</string>
    <string name="profiler_no_storage_toast">"No es posible iniciar el analizador por que el almacenamiento externo no está listo"</string>
    <string name="profiler_error_toast">"Fallo al iniciar analizador"</string>
    <string name="low_memory_error">"No hay suficiente memoria para completar esta tarea"</string>
    <string name="opening_file_error">"Fallo al abrir el archivo seleccionado"</string>
    <string name="color_picker_button_more">"Más"</string>
    <string name="color_picker_hue">"Matíz"</string>
    <string name="color_picker_saturation">"Saturación"</string>
    <string name="color_picker_value">"Valor"</string>
    <string name="color_picker_button_set">"Asignar"</string>
    <string name="color_picker_button_cancel">"Cancelar"</string>
    <string name="color_picker_dialog_title">"Seleccionar color"</string>
    <string name="color_picker_button_red">"Rojo"</string>
    <string name="color_picker_button_cyan">"Celeste"</string>
    <string name="color_picker_button_blue">"Azul"</string>
    <string name="color_picker_button_green">"Verde"</string>
    <string name="color_picker_button_magenta">"Lila"</string>
    <string name="color_picker_button_yellow">"Amarillo"</string>
    <string name="color_picker_button_black">"Negro"</string>
    <string name="color_picker_button_white">"Blanco"</string>
    <string name="date_picker_dialog_other_button_label">"Otros"</string>
    <string name="copy_to_clipboard_failure_message">"Fallo al copiar al portapapeles"</string>
    <string name="miuichromium_error_page_title">No es posible encontrar la página</string>
    <string name="miuichromium_error_page_reason_network">Ver enlace URL</string>
    <string name="miuichromium_error_page_mobile">Redes móviles</string>
    <string name="miuichromium_error_page_wlan">Ajustes Wi-Fi</string>
    <string name="miuichromium_error_page_reason_server">El navegador no puede cargar esta página</string>
    <string name="miuichromium_error_page_reload">Recargar</string>
    <string name="miuichromium_error_page_url">Ver página URL</string>
    <string name="config_webSettingsDefaultTextEncoding">UTF-8</string>
    <string name="webviewchromium_private_browsing_warning">La función no es compatible con esta versión de Android.</string>
    <string name="save_password_message">¿Quieres  que el Navegador recuerde esta contraseña?</string>
    <string name="save_password_notnow">Ahora no</string>
    <string name="save_password_remember">Recordar</string>
    <string name="save_password_never">Nunca</string>
    <string name="private_browsing_warning">"Esta funcionalidad no está soportada en esta versión de Android."</string>
    <string name="miui_content_select">Seleccionar</string>
    <string name="miui_content_select_all">Seleccionar todo</string>
    <string name="miui_content_cut">Cortar</string>
    <string name="miui_content_copy">Copiar</string>
    <string name="miui_content_paste">Pegar</string>
    <string name="miui_content_web_search">Buscar</string>
    <string name="miui_content_share">Compartir</string>
    <plurals name="last_num_days">
        <item quantity="other">Últimos <xliff:g id="count">%d</xliff:g> días</item>
        <item quantity="one">Ayer</item>
    </plurals>
    <string name="last_month">Último mes</string>
    <string name="older">Antiguos</string>
    <string name="js_dialog_title">Esta página: \"<xliff:g id="title">%s</xliff:g>\" dice:</string>
    <string name="js_dialog_title_default">JavaScript</string>
    <string name="js_dialog_before_unload_title">Confirmar navegación</string>
    <string name="js_dialog_before_unload_positive_button">Dejar esta página</string>
    <string name="js_dialog_before_unload_negative_button">Permanecer en esta página</string>
    <string name="js_dialog_before_unload"><xliff:g id="message">%s</xliff:g>\n\n¿Está seguro de que desea abandonar esta página?</string>
    <string name="find_next">Encontrar siguiente</string>
    <string name="find_previous">Encontrar anterior</string>
    <string name="no_matches">Sin coincidencias</string>
    <plurals name="matches_found">
        <item quantity="one">1 coincidencia</item>
        <item quantity="other">




      <xliff:g example="2" id="index">%d</xliff:g>


      de


      <xliff:g example="137" id="total">%d</xliff:g>




    </item>
    </plurals>
    <string name="webview_find_on_page">Buscar en la página</string>
    <string name="miui_content_open_url">Abrir URL</string>
    <string name="miuichromium_error_page_diagnostic">Network diagnostic</string>
</resources>
